testbandit/__init__.py
testbandit/experiment.py
testbandit-0.1.1.dist-info/METADATA
testbandit-0.1.1.dist-info/WHEEL
testbandit-0.1.1.dist-info/top_level.txt
testbandit-0.1.1.dist-info/RECORD
